fr_youssef_test_cf/__init__.py
fr_youssef_test_cf/clickhoused.py
fr_youssef_test_cf/core_env_vars.py
fr_youssef_test_cf/data_transformer.py
fr_youssef_test_cf/enappsys.py
fr_youssef_test_cf/env_vars.py
fr_youssef_test_cf/minio_driver.py
fr_youssef_test_cf/plugin_loader.py
fr_youssef_test_cf/util.py
fr_youssef_test_cf-2.0.12.dist-info/METADATA
fr_youssef_test_cf-2.0.12.dist-info/WHEEL
fr_youssef_test_cf-2.0.12.dist-info/top_level.txt
fr_youssef_test_cf-2.0.12.dist-info/RECORD
